neuraparse_universal_scraper-0.1.1-py3.12-nspkg.pth
neuraparse/universal_scraper/__init__.py
neuraparse/universal_scraper/scraper.py
neuraparse_universal_scraper-0.1.1.dist-info/METADATA
neuraparse_universal_scraper-0.1.1.dist-info/WHEEL
neuraparse_universal_scraper-0.1.1.dist-info/entry_points.txt
neuraparse_universal_scraper-0.1.1.dist-info/namespace_packages.txt
neuraparse_universal_scraper-0.1.1.dist-info/top_level.txt
neuraparse_universal_scraper-0.1.1.dist-info/RECORD
