Metadata-Version: 2.2
Name: neuraparse-universal-scraper
Version: 0.1.1
Summary: Universal web scraper package under neuraparse namespace
Home-page: https://github.com/kullaniciadi/neuraparse-universal-scraper
Author: Adınız
Author-email: email@example.com
Classifier: Programming Language :: Python :: 3
Classifier: Operating System :: OS Independent
Requires-Python: >=3.6
Requires-Dist: selenium
Requires-Dist: beautifulsoup4
Requires-Dist: requests
Requires-Dist: lxml
Requires-Dist: html5lib
Requires-Dist: undetected-chromedriver
Dynamic: author
Dynamic: author-email
Dynamic: classifier
Dynamic: description
Dynamic: description-content-type
Dynamic: home-page
Dynamic: requires-dist
Dynamic: requires-python
Dynamic: summary
